COPYING
MANIFEST.in
README.rst
TODO
setup.py
django_milcam.egg-info/PKG-INFO
django_milcam.egg-info/SOURCES.txt
django_milcam.egg-info/dependency_links.txt
django_milcam.egg-info/not-zip-safe
django_milcam.egg-info/requires.txt
django_milcam.egg-info/top_level.txt
milcam/__init__.py
milcam/admin.py
milcam/api.py
milcam/context_processors.py
milcam/forms.py
milcam/settings.py
milcam/urls.py
milcam/views.py
milcam/locale/en/LC_MESSAGES/django.po
milcam/locale/uk/LC_MESSAGES/django.po
milcam/migrations/0001_initial.py
milcam/migrations/0002_auto__chg_field_photo_created.py
milcam/migrations/__init__.py
milcam/models/__init__.py
milcam/models/device.py
milcam/models/photo.py
milcam/static/milcam/js/models.js
milcam/static/milcam/js/views.js
milcam/static/milcam/lib/backbone/backbone-min.js
milcam/static/milcam/lib/backbone/backbone.js
milcam/static/milcam/lib/backbone-relational/backbone-relational.js
milcam/static/milcam/lib/backbone-tastypie/backbone-tastypie.js
milcam/static/milcam/lib/bootstrap/css/bootstrap-theme.css
milcam/static/milcam/lib/bootstrap/css/bootstrap-theme.css.map
milcam/static/milcam/lib/bootstrap/css/bootstrap-theme.min.css
milcam/static/milcam/lib/bootstrap/css/bootstrap.css
milcam/static/milcam/lib/bootstrap/css/bootstrap.css.map
milcam/static/milcam/lib/bootstrap/css/bootstrap.min.css
milcam/static/milcam/lib/bootstrap/fonts/glyphicons-halflings-regular.eot
milcam/static/milcam/lib/bootstrap/fonts/glyphicons-halflings-regular.svg
milcam/static/milcam/lib/bootstrap/fonts/glyphicons-halflings-regular.ttf
milcam/static/milcam/lib/bootstrap/fonts/glyphicons-halflings-regular.woff
milcam/static/milcam/lib/bootstrap/js/bootstrap.js
milcam/static/milcam/lib/bootstrap/js/bootstrap.min.js
milcam/static/milcam/lib/html5shim/html5shiv-printshiv.js
milcam/static/milcam/lib/html5shim/html5shiv.js
milcam/static/milcam/lib/jquery/jquery-1.11.1.js
milcam/static/milcam/lib/jquery/jquery-1.11.1.min.js
milcam/static/milcam/lib/jquery/jquery-1.11.1.min.map
milcam/static/milcam/lib/jquery-cookie/jquery.cookie-1.4.1.min.js
milcam/static/milcam/lib/jquery-cookie/jquery.cookie.js
milcam/static/milcam/lib/js-base64/base64.js
milcam/static/milcam/lib/js-base64/base64.min.js
