Metadata-Version: 1.1
Name: django-milcam
Version: 0.3.1
Summary: Military Camera project
Home-page: https://github.com/anonymous-ukrainian-patriot/django-milcam/
Author: Anonymous Ukrainian Patriot
Author-email: anonymous.ukrainian.patriot@gmail.com
License: GPLv3 or later
Download-URL: https://github.com/anonymous-ukrainian-patriot/django-milcam/archive/0.3.1.tar.gz
Platform: UNKNOWN
Classifier: Environment :: Plugins
Classifier: License :: OSI Approved :: GNU General Public License v3 or later (GPLv3+)
Classifier: Operating System :: Unix
Classifier: Programming Language :: Python :: 2.6
Classifier: Programming Language :: Python :: 2.7
Classifier: Topic :: Utilities
